Workbook

Sheet Dashboard
B1: 📊 SALES PERFORMANCE DASHBOARD
B2: Powered by real PivotTables (Region · Month · Product · Category) · filter with slicers in the left panel
B5: 🎛 FILTERS (SLICERS) | E5: 💰 TOTAL REVENUE | G5: 📈 TOTAL PROFIT | I5: 🎯 PROFIT MARGIN | K5: 🛒 ORDERS | M5: 🧾 AVG ORDER VALUE
B6: 1 Click any PivotTable on the 'Pivots' sheet. | E6: =Calc!B9 -> 24289864 | G6: =Calc!C9 -> 6356344.5 | I6: =IF(Calc!B9=0,0,Calc!C9/Calc!B9) -> 0.26168711 | K6: =Calc!D9 -> 900 | M6: =IF(Calc!D9=0,0,Calc!B9/Calc!D9) -> 26988.738
E8: ="Top region: "&INDEX(Calc!A4:A8,MATCH(MAX(Calc!B4:B8),Calc!B4:B8,0)) -> Top region: South | G8: ="Best month: "&INDEX(Calc!A13:A24,MATCH(MAX(Calc!B13:B24),Calc!B13:B24,0)) -> Best month: 11 Nov | I8: Profit ÷ Revenue | K8: Order lines | M8: Revenue ÷ Orders
B9: 2 PivotTable Analyze ▸ Insert Slicer ▸ tick Year, Region and Category.
E10: PERFORMANCE OVERVIEW
B12: 3 Slicer ▸ Report Connections ▸ tick all 4 PivotTables.
B15: 4 Cut the slicers and paste them into the zone below.
B19: SLICER ZONE (Year · Region · Category)
E43: 🌍 REGION SCORECARD | J43: 🏆 TOP 5 PRODUCTS
E44: Region | F44: Revenue | G44: Profit | H44: Margin | I44: Share | J44: Rank | K44: Product | M44: Revenue | N44: Share
E45: =Calc!A4 -> Central | F45: =Calc!B4 -> 2720063.5 | G45: =Calc!C4 -> 738653.5 | H45: =IF(Calc!B4=0,0,Calc!C4/Calc!B4) -> 0.27155745 | I45: =IF(Calc!$B$9=0,0,Calc!B4/Calc!$B$9) -> 0.11198348 | J45: =CHOOSE(1,"🥇","🥈","🥉","4","5") -> 🥇 | K45: =Calc!H35 -> Laptop | M45: =Calc!I35 -> 7053989.5 | N45: =IF(Calc!$B$9=0,0,M45/Calc!$B$9) -> 0.29040876
E46: =Calc!A5 -> East | F46: =Calc!B5 -> 3409733 | G46: =Calc!C5 -> 905793 | H46: =IF(Calc!B5=0,0,Calc!C5/Calc!B5) -> 0.26564925 | I46: =IF(Calc!$B$9=0,0,Calc!B5/Calc!$B$9) -> 0.14037678 | J46: =CHOOSE(2,"🥇","🥈","🥉","4","5") -> 🥈 | K46: =Calc!H36 -> Smartphone | M46: =Calc!I36 -> 4855275.5 | N46: =IF(Calc!$B$9=0,0,M46/Calc!$B$9) -> 0.19988895
E47: =Calc!A6 -> North | F47: =Calc!B6 -> 6207313 | G47: =Calc!C6 -> 1687633 | H47: =IF(Calc!B6=0,0,Calc!C6/Calc!B6) -> 0.27187819 | I47: =IF(Calc!$B$9=0,0,Calc!B6/Calc!$B$9) -> 0.25555157 | J47: =CHOOSE(3,"🥇","🥈","🥉","4","5") -> 🥉 | K47: =Calc!H37 -> Office Chair | M47: =Calc!I37 -> 2083738 | N47: =IF(Calc!$B$9=0,0,M47/Calc!$B$9) -> 0.085786316
E48: =Calc!A7 -> South | F48: =Calc!B7 -> 7004880.5 | G48: =Calc!C7 -> 1734580.5 | H48: =IF(Calc!B7=0,0,Calc!C7/Calc!B7) -> 0.24762457 | I48: =IF(Calc!$B$9=0,0,Calc!B7/Calc!$B$9) -> 0.28838697 | J48: =CHOOSE(4,"🥇","🥈","🥉","4","5") -> 4 | K48: =Calc!H38 -> Standing Desk | M48: =Calc!I38 -> 1840267.5 | N48: =IF(Calc!$B$9=0,0,M48/Calc!$B$9) -> 0.075762773
E49: =Calc!A8 -> West | F49: =Calc!B8 -> 4947874.5 | G49: =Calc!C8 -> 1289684.5 | H49: =IF(Calc!B8=0,0,Calc!C8/Calc!B8) -> 0.26065425 | I49: =IF(Calc!$B$9=0,0,Calc!B8/Calc!$B$9) -> 0.2037012 | J49: =CHOOSE(5,"🥇","🥈","🥉","4","5") -> 5 | K49: =Calc!H39 -> Air Purifier | M49: =Calc!I39 -> 1537535.5 | N49: =IF(Calc!$B$9=0,0,M49/Calc!$B$9) -> 0.063299468
B51: Source: Sales_Data → PivotTables (Pivots sheet) → Calc → Dashboard. Revenue = Quantity × Unit Price × (1 − Discount). Amounts in ₹. Chart axes in millions (M). Sample data is synthetic.

Sheet Pivots
A1: PIVOTTABLES — real Excel PivotTables built from Sales_Data (right-click a pivot ▸ Refresh after changing data)
A3: 🌍 Sales by Region | G3: 📅 Sales by Month | L3: 📦 Sales by Product
B5: Data | H5: Data | M5: Data
A6: Region | B6: Sum - Revenue | C6: Sum - Profit | D6: Count - Order ID | G6: Month | H6: Sum - Revenue | I6: Sum - Profit | L6: Product | M6: Sum - Revenue | N6: Sum - Profit
A7: Central | B7: 2720063.5 | C7: 738653.5 | D7: 109 | G7: 01 Jan | H7: 1620607 | I7: 441707 | L7: Air Purifier | M7: 1537535.5 | N7: 445035.5
A8: East | B8: 3409733 | C8: 905793 | D8: 116 | G8: 02 Feb | H8: 1752835 | I8: 482495 | L8: Bookshelf | M8: 968528.5 | N8: 313328.5
A9: North | B9: 6207313 | C9: 1687633 | D9: 247 | G9: 03 Mar | H9: 1886227 | I9: 507527 | L9: Desk Organizer | M9: 643430.5 | N9: 277110.5
A10: South | B10: 7004880.5 | C10: 1734580.5 | D10: 243 | G10: 04 Apr | H10: 1650096 | I10: 421216 | L10: Gel Pen Box | M10: 729076 | N10: 321076
A11: West | B11: 4947874.5 | C11: 1289684.5 | D11: 185 | G11: 05 May | H11: 2119832 | I11: 544552 | L11: Laptop | M11: 7053989.5 | N11: 1383989.5
A12: Total Result | B12: 24289864 | C12: 6356344.5 | D12: 900 | G12: 06 Jun | H12: 1678147.5 | I12: 435907.5 | L12: Microwave Oven | M12: 1482889.5 | N12: 346889.5
G13: 07 Jul | H13: 1346851.5 | I13: 346971.5 | L13: Notebook Pack | M13: 901982.5 | N13: 374982.5
A14: 🏷️ Sales by Category | G14: 08 Aug | H14: 1714494.5 | I14: 426174.5 | L14: Office Chair | M14: 2083738 | N14: 625738
G15: 09 Sep | H15: 2031742.5 | I15: 565342.5 | L15: Smartphone | M15: 4855275.5 | N15: 1003275.5
B16: Data | G16: 10 Oct | H16: 2577860.5 | I16: 680360.5 | L16: Standing Desk | M16: 1840267.5 | N16: 502767.5
A17: Category | B17: Sum - Revenue | C17: Sum - Profit | G17: 11 Nov | H17: 3173388 | I17: 820838 | L17: Water Purifier | M17: 1295197.5 | N17: 404197.5
A18: Appliances | B18: 4315622.5 | C18: 1196122.5 | G18: 12 Dec | H18: 2737783 | I18: 683253 | L18: Wireless Earbuds | M18: 897954 | N18: 357954
A19: Electronics | B19: 12807219 | C19: 2745219 | G19: Total Result | H19: 24289864 | I19: 6356344.5 | L19: Total Result | M19: 24289864 | N19: 6356344.5
A20: Furniture | B20: 4892534 | C20: 1441834
A21: Stationery | B21: 2274489 | C21: 973169
A22: Total Result | B22: 24289864 | C22: 6356344.5

Sheet Calc
A1: Calculation layer — reads the PivotTables on the 'Pivots' sheet and ignores their Total rows, so charts stay correct when slicers shrink a pivot.
A2: Region
A3: Region | B3: Revenue | C3: Profit | D3: Orders
A4: =IF(OR(Pivots!A7="Grand Total",Pivots!A7="Total Result",Pivots!A7=""),"",Pivots!A7&"") -> Central | B4: =IF($A4="",0,N(Pivots!B7)) -> 2720063.5 | C4: =IF($A4="",0,N(Pivots!C7)) -> 738653.5 | D4: =IF($A4="",0,N(Pivots!D7)) -> 109
A5: =IF(OR(Pivots!A8="Grand Total",Pivots!A8="Total Result",Pivots!A8=""),"",Pivots!A8&"") -> East | B5: =IF($A5="",0,N(Pivots!B8)) -> 3409733 | C5: =IF($A5="",0,N(Pivots!C8)) -> 905793 | D5: =IF($A5="",0,N(Pivots!D8)) -> 116
A6: =IF(OR(Pivots!A9="Grand Total",Pivots!A9="Total Result",Pivots!A9=""),"",Pivots!A9&"") -> North | B6: =IF($A6="",0,N(Pivots!B9)) -> 6207313 | C6: =IF($A6="",0,N(Pivots!C9)) -> 1687633 | D6: =IF($A6="",0,N(Pivots!D9)) -> 247
A7: =IF(OR(Pivots!A10="Grand Total",Pivots!A10="Total Result",Pivots!A10=""),"",Pivots!A10&"") -> South | B7: =IF($A7="",0,N(Pivots!B10)) -> 7004880.5 | C7: =IF($A7="",0,N(Pivots!C10)) -> 1734580.5 | D7: =IF($A7="",0,N(Pivots!D10)) -> 243
A8: =IF(OR(Pivots!A11="Grand Total",Pivots!A11="Total Result",Pivots!A11=""),"",Pivots!A11&"") -> West | B8: =IF($A8="",0,N(Pivots!B11)) -> 4947874.5 | C8: =IF($A8="",0,N(Pivots!C11)) -> 1289684.5 | D8: =IF($A8="",0,N(Pivots!D11)) -> 185
A9: Total | B9: =SUM(B4:B8) -> 24289864 | C9: =SUM(C4:C8) -> 6356344.5 | D9: =SUM(D4:D8) -> 900
A12: Month | B12: Revenue | C12: Profit
A13: =IF(OR(Pivots!G7="Grand Total",Pivots!G7="Total Result",Pivots!G7=""),"",Pivots!G7&"") -> 01 Jan | B13: =IF($A13="",0,N(Pivots!H7)) -> 1620607 | C13: =IF($A13="",0,N(Pivots!I7)) -> 441707
A14: =IF(OR(Pivots!G8="Grand Total",Pivots!G8="Total Result",Pivots!G8=""),"",Pivots!G8&"") -> 02 Feb | B14: =IF($A14="",0,N(Pivots!H8)) -> 1752835 | C14: =IF($A14="",0,N(Pivots!I8)) -> 482495
A15: =IF(OR(Pivots!G9="Grand Total",Pivots!G9="Total Result",Pivots!G9=""),"",Pivots!G9&"") -> 03 Mar | B15: =IF($A15="",0,N(Pivots!H9)) -> 1886227 | C15: =IF($A15="",0,N(Pivots!I9)) -> 507527
A16: =IF(OR(Pivots!G10="Grand Total",Pivots!G10="Total Result",Pivots!G10=""),"",Pivots!G10&"") -> 04 Apr | B16: =IF($A16="",0,N(Pivots!H10)) -> 1650096 | C16: =IF($A16="",0,N(Pivots!I10)) -> 421216
A17: =IF(OR(Pivots!G11="Grand Total",Pivots!G11="Total Result",Pivots!G11=""),"",Pivots!G11&"") -> 05 May | B17: =IF($A17="",0,N(Pivots!H11)) -> 2119832 | C17: =IF($A17="",0,N(Pivots!I11)) -> 544552
A18: =IF(OR(Pivots!G12="Grand Total",Pivots!G12="Total Result",Pivots!G12=""),"",Pivots!G12&"") -> 06 Jun | B18: =IF($A18="",0,N(Pivots!H12)) -> 1678147.5 | C18: =IF($A18="",0,N(Pivots!I12)) -> 435907.5
A19: =IF(OR(Pivots!G13="Grand Total",Pivots!G13="Total Result",Pivots!G13=""),"",Pivots!G13&"") -> 07 Jul | B19: =IF($A19="",0,N(Pivots!H13)) -> 1346851.5 | C19: =IF($A19="",0,N(Pivots!I13)) -> 346971.5
A20: =IF(OR(Pivots!G14="Grand Total",Pivots!G14="Total Result",Pivots!G14=""),"",Pivots!G14&"") -> 08 Aug | B20: =IF($A20="",0,N(Pivots!H14)) -> 1714494.5 | C20: =IF($A20="",0,N(Pivots!I14)) -> 426174.5
A21: =IF(OR(Pivots!G15="Grand Total",Pivots!G15="Total Result",Pivots!G15=""),"",Pivots!G15&"") -> 09 Sep | B21: =IF($A21="",0,N(Pivots!H15)) -> 2031742.5 | C21: =IF($A21="",0,N(Pivots!I15)) -> 565342.5
A22: =IF(OR(Pivots!G16="Grand Total",Pivots!G16="Total Result",Pivots!G16=""),"",Pivots!G16&"") -> 10 Oct | B22: =IF($A22="",0,N(Pivots!H16)) -> 2577860.5 | C22: =IF($A22="",0,N(Pivots!I16)) -> 680360.5
A23: =IF(OR(Pivots!G17="Grand Total",Pivots!G17="Total Result",Pivots!G17=""),"",Pivots!G17&"") -> 11 Nov | B23: =IF($A23="",0,N(Pivots!H17)) -> 3173388 | C23: =IF($A23="",0,N(Pivots!I17)) -> 820838
A24: =IF(OR(Pivots!G18="Grand Total",Pivots!G18="Total Result",Pivots!G18=""),"",Pivots!G18&"") -> 12 Dec | B24: =IF($A24="",0,N(Pivots!H18)) -> 2737783 | C24: =IF($A24="",0,N(Pivots!I18)) -> 683253
A27: Category | B27: Revenue | C27: Profit
A28: =IF(OR(Pivots!A18="Grand Total",Pivots!A18="Total Result",Pivots!A18=""),"",Pivots!A18&"") -> Appliances | B28: =IF($A28="",0,N(Pivots!B18)) -> 4315622.5 | C28: =IF($A28="",0,N(Pivots!C18)) -> 1196122.5
A29: =IF(OR(Pivots!A19="Grand Total",Pivots!A19="Total Result",Pivots!A19=""),"",Pivots!A19&"") -> Electronics | B29: =IF($A29="",0,N(Pivots!B19)) -> 12807219 | C29: =IF($A29="",0,N(Pivots!C19)) -> 2745219
A30: =IF(OR(Pivots!A20="Grand Total",Pivots!A20="Total Result",Pivots!A20=""),"",Pivots!A20&"") -> Furniture | B30: =IF($A30="",0,N(Pivots!B20)) -> 4892534 | C30: =IF($A30="",0,N(Pivots!C20)) -> 1441834
A31: =IF(OR(Pivots!A21="Grand Total",Pivots!A21="Total Result",Pivots!A21=""),"",Pivots!A21&"") -> Stationery | B31: =IF($A31="",0,N(Pivots!B21)) -> 2274489 | C31: =IF($A31="",0,N(Pivots!C21)) -> 973169
A34: Product | B34: Revenue | C34: Profit | E34: Sort key | G34: Rank | H34: Product | I34: Revenue | J34: Row idx
A35: =IF(OR(Pivots!L7="Grand Total",Pivots!L7="Total Result",Pivots!L7=""),"",Pivots!L7&"") -> Air Purifier | B35: =IF($A35="",0,N(Pivots!M7)) -> 1537535.5 | C35: =IF($A35="",0,N(Pivots!N7)) -> 445035.5 | E35: =B35+ROW()/1000000 -> 1537535.5 | G35: 1 | H35: =IF(I35=0,"-",INDEX($A$35:$A$46,J35)) -> Laptop | I35: =INDEX($B$35:$B$46,J35) -> 7053989.5 | J35: =MATCH(LARGE($E$35:$E$46,G35),$E$35:$E$46,0) -> 5
A36: =IF(OR(Pivots!L8="Grand Total",Pivots!L8="Total Result",Pivots!L8=""),"",Pivots!L8&"") -> Bookshelf | B36: =IF($A36="",0,N(Pivots!M8)) -> 968528.5 | C36: =IF($A36="",0,N(Pivots!N8)) -> 313328.5 | E36: =B36+ROW()/1000000 -> 968528.5 | G36: 2 | H36: =IF(I36=0,"-",INDEX($A$35:$A$46,J36)) -> Smartphone | I36: =INDEX($B$35:$B$46,J36) -> 4855275.5 | J36: =MATCH(LARGE($E$35:$E$46,G36),$E$35:$E$46,0) -> 9
A37: =IF(OR(Pivots!L9="Grand Total",Pivots!L9="Total Result",Pivots!L9=""),"",Pivots!L9&"") -> Desk Organizer | B37: =IF($A37="",0,N(Pivots!M9)) -> 643430.5 | C37: =IF($A37="",0,N(Pivots!N9)) -> 277110.5 | E37: =B37+ROW()/1000000 -> 643430.5 | G37: 3 | H37: =IF(I37=0,"-",INDEX($A$35:$A$46,J37)) -> Office Chair | I37: =INDEX($B$35:$B$46,J37) -> 2083738 | J37: =MATCH(LARGE($E$35:$E$46,G37),$E$35:$E$46,0) -> 8
A38: =IF(OR(Pivots!L10="Grand Total",Pivots!L10="Total Result",Pivots!L10=""),"",Pivots!L10&"") -> Gel Pen Box | B38: =IF($A38="",0,N(Pivots!M10)) -> 729076 | C38: =IF($A38="",0,N(Pivots!N10)) -> 321076 | E38: =B38+ROW()/1000000 -> 729076 | G38: 4 | H38: =IF(I38=0,"-",INDEX($A$35:$A$46,J38)) -> Standing Desk | I38: =INDEX($B$35:$B$46,J38) -> 1840267.5 | J38: =MATCH(LARGE($E$35:$E$46,G38),$E$35:$E$46,0) -> 10
A39: =IF(OR(Pivots!L11="Grand Total",Pivots!L11="Total Result",Pivots!L11=""),"",Pivots!L11&"") -> Laptop | B39: =IF($A39="",0,N(Pivots!M11)) -> 7053989.5 | C39: =IF($A39="",0,N(Pivots!N11)) -> 1383989.5 | E39: =B39+ROW()/1000000 -> 7053989.5 | G39: 5 | H39: =IF(I39=0,"-",INDEX($A$35:$A$46,J39)) -> Air Purifier | I39: =INDEX($B$35:$B$46,J39) -> 1537535.5 | J39: =MATCH(LARGE($E$35:$E$46,G39),$E$35:$E$46,0) -> 1
A40: =IF(OR(Pivots!L12="Grand Total",Pivots!L12="Total Result",Pivots!L12=""),"",Pivots!L12&"") -> Microwave Oven | B40: =IF($A40="",0,N(Pivots!M12)) -> 1482889.5 | C40: =IF($A40="",0,N(Pivots!N12)) -> 346889.5 | E40: =B40+ROW()/1000000 -> 1482889.5
A41: =IF(OR(Pivots!L13="Grand Total",Pivots!L13="Total Result",Pivots!L13=""),"",Pivots!L13&"") -> Notebook Pack | B41: =IF($A41="",0,N(Pivots!M13)) -> 901982.5 | C41: =IF($A41="",0,N(Pivots!N13)) -> 374982.5 | E41: =B41+ROW()/1000000 -> 901982.5
A42: =IF(OR(Pivots!L14="Grand Total",Pivots!L14="Total Result",Pivots!L14=""),"",Pivots!L14&"") -> Office Chair | B42: =IF($A42="",0,N(Pivots!M14)) -> 2083738 | C42: =IF($A42="",0,N(Pivots!N14)) -> 625738 | E42: =B42+ROW()/1000000 -> 2083738
A43: =IF(OR(Pivots!L15="Grand Total",Pivots!L15="Total Result",Pivots!L15=""),"",Pivots!L15&"") -> Smartphone | B43: =IF($A43="",0,N(Pivots!M15)) -> 4855275.5 | C43: =IF($A43="",0,N(Pivots!N15)) -> 1003275.5 | E43: =B43+ROW()/1000000 -> 4855275.5
A44: =IF(OR(Pivots!L16="Grand Total",Pivots!L16="Total Result",Pivots!L16=""),"",Pivots!L16&"") -> Standing Desk | B44: =IF($A44="",0,N(Pivots!M16)) -> 1840267.5 | C44: =IF($A44="",0,N(Pivots!N16)) -> 502767.5 | E44: =B44+ROW()/1000000 -> 1840267.5
A45: =IF(OR(Pivots!L17="Grand Total",Pivots!L17="Total Result",Pivots!L17=""),"",Pivots!L17&"") -> Water Purifier | B45: =IF($A45="",0,N(Pivots!M17)) -> 1295197.5 | C45: =IF($A45="",0,N(Pivots!N17)) -> 404197.5 | E45: =B45+ROW()/1000000 -> 1295197.5
A46: =IF(OR(Pivots!L18="Grand Total",Pivots!L18="Total Result",Pivots!L18=""),"",Pivots!L18&"") -> Wireless Earbuds | B46: =IF($A46="",0,N(Pivots!M18)) -> 897954 | C46: =IF($A46="",0,N(Pivots!N18)) -> 357954 | E46: =B46+ROW()/1000000 -> 897954

Sheet Sales_Data
A1: Order ID | B1: Order Date | C1: Year | D1: Month | E1: Region | F1: Category | G1: Product | H1: Sales Rep | I1: Quantity | J1: Unit Price | K1: Discount % | L1: Unit Cost | M1: Revenue | N1: Cost | O1: Profit
A2: ORD-0001 | B2: 44927 | C2: =YEAR(B2) -> 2023 | D2: =CHOOSE(MONTH(B2),"01 Jan","02 Feb","03 Mar","04 Apr","05 May","06 Jun","07 Jul","08 Aug","09 Sep","10 Oct","11 Nov","12 Dec") -> 01 Jan | E2: South | F2: Stationery | G2: Desk Organizer | H2: Divya Nair | I2: 8 | J2: 690 | K2: 0.05 | L2: 380 | M2: =I2*J2*(1-K2) -> 5244 | N2: =I2*L2 -> 3040 | O2: =M2-N2 -> 2204
A3: ORD-0002 | B3: 44928 | C3: =YEAR(B3) -> 2023 | D3: =CHOOSE(MONTH(B3),"01 Jan","02 Feb","03 Mar","04 Apr","05 May","06 Jun","07 Jul","08 Aug","09 Sep","10 Oct","11 Nov","12 Dec") -> 01 Jan | E3: North | F3: Stationery | G3: Notebook Pack | H3: Aarav Sharma | I3: 7 | J3: 430 | K3: 0.05 | L3: 250 | M3: =I3*J3*(1-K3) -> 2859.5 | N3: =I3*L3 -> 1750 | O3: =M3-N3 -> 1109.5
A4: ORD-0003 | B4: 44929 | C4: =YEAR(B4) -> 2023 | D4: =CHOOSE(MONTH(B4),"01 Jan","02 Feb","03 Mar","04 Apr","05 May","06 Jun","07 Jul","08 Aug","09 Sep","10 Oct","11 Nov","12 Dec") -> 01 Jan | E4: Central | F4: Furniture | G4: Office Chair | H4: Sneha Joshi | I4: 5 | J4: 8600 | K4: 0 | L4: 6000 | M4: =I4*J4*(1-K4) -> 43000 | N4: =I4*L4 -> 30000 | O4: =M4-N4 -> 13000
A5: ORD-0004 | B5: 44933 | C5: =YEAR(B5) -> 2023 | D5: =CHOOSE(MONTH(B5),"01 Jan","02 Feb","03 Mar","04 Apr","05 May","06 Jun","07 Jul","08 Aug","09 Sep","10 Oct","11 Nov","12 Dec") -> 01 Jan | E5: South | F5: Furniture | G5: Bookshelf | H5: Karthik Iyer | I5: 4 | J5: 6810 | K5: 0.1 | L5: 4200 | M5: =I5*J5*(1-K5) -> 24516 | N5: =I5*L5 -> 16800 | O5: =M5-N5 -> 7716
A6: ORD-0005 | B6: 44936 | C6: =YEAR(B6) -> 2023 | D6: =CHOOSE(MONTH(B6),"01 Jan","02 Feb","03 Mar","04 Apr","05 May","06 Jun","07 Jul","08 Aug","09 Sep","10 Oct","11 Nov","12 Dec") -> 01 Jan | E6: West | F6: Stationery | G6: Notebook Pack | H6: Pooja Mehta | I6: 17 | J6: 440 | K6: 0.15 | L6: 250 | M6: =I6*J6*(1-K6) -> 6358 | N6: =I6*L6 -> 4250 | O6: =M6-N6 -> 2108
A7: ORD-0006 | B7: 44940 | C7: =YEAR(B7) -> 2023 | D7: =CHOOSE(MONTH(B7),"01 Jan","02 Feb","03 Mar","04 Apr","05 May","06 Jun","07 Jul","08 Aug","09 Sep","10 Oct","11 Nov","12 Dec") -> 01 Jan | E7: North | F7: Stationery | G7: Gel Pen Box | H7: Aarav Sharma | I7: 29 | J7: 290 | K7: 0 | L7: 160 | M7: =I7*J7*(1-K7) -> 8410 | N7: =I7*L7 -> 4640 | O7: =M7-N7 -> 3770
A8: ORD-0007 | B8: 44941 | C8: =YEAR(B8) -> 2023 | D8: =CHOOSE(MONTH(B8),"01 Jan","02 Feb","03 Mar","04 Apr","05 May","06 Jun","07 Jul","08 Aug","09 Sep","10 Oct","11 Nov","12 Dec") -> 01 Jan | E8: West | F8: Stationery | G8: Notebook Pack | H8: Rohan Patil | I8: 14 | J8: 450 | K8: 0.1 | L8: 250 | M8: =I8*J8*(1-K8) -> 5670 | N8: =I8*L8 -> 3500 | O8: =M8-N8 -> 2170
A9: ORD-0008 | B9: 44944 | C9: =YEAR(B9) -> 2023 | D9: =CHOOSE(MONTH(B9),"01 Jan","02 Feb","03 Mar","04 Apr","05 May","06 Jun","07 Jul","08 Aug","09 Sep","10 Oct","11 Nov","12 Dec") -> 01 Jan | E9: East | F9: Electronics | G9: Laptop | H9: Subhash Das | I9: 1 | J9: 53710 | K9: 0 | L9: 42000 | M9: =I9*J9*(1-K9) -> 53710 | N9: =I9*L9 -> 42000 | O9: =M9-N9 -> 11710
A10: ORD-0009 | B10: 44944 | C10: =YEAR(B10) -> 2023 | D10: =CHOOSE(MONTH(B10),"01 Jan","02 Feb","03 Mar","04 Apr","05 May","06 Jun","07 Jul","08 Aug","09 Sep","10 Oct","11 Nov","12 Dec") -> 01 Jan | E10: North | F10: Electronics | G10: Smartphone | H10: Aarav Sharma | I10: 1 | J10: 22830 | K10: 0.05 | L10: 18000 | M10: =I10*J10*(1-K10) -> 21688.5 | N10: =I10*L10 -> 18000 | O10: =M10-N10 -> 3688.5
A11: ORD-0010 | B11: 44945 | C11: =YEAR(B11) -> 2023 | D11: =CHOOSE(MONTH(B11),"01 Jan","02 Feb","03 Mar","04 Apr","05 May","06 Jun","07 Jul","08 Aug","09 Sep","10 Oct","11 Nov","12 Dec") -> 01 Jan | E11: West | F11: Furniture | G11: Office Chair | H11: Pooja Mehta | I11: 4 | J11: 8650 | K11: 0.05 | L11: 6000 | M11: =I11*J11*(1-K11) -> 32870 | N11: =I11*L11 -> 24000 | O11: =M11-N11 -> 8870
A12: ORD-0011 | B12: 44947 | C12: =YEAR(B12) -> 2023 | D12: =CHOOSE(MONTH(B12),"01 Jan","02 Feb","03 Mar","04 Apr","05 May","06 Jun","07 Jul","08 Aug","09 Sep","10 Oct","11 Nov","12 Dec") -> 01 Jan | E12: North | F12: Appliances | G12: Microwave Oven | H12: Aarav Sharma | I12: 2 | J12: 11380 | K12: 0.1 | L12: 8000 | M12: =I12*J12*(1-K12) -> 20484 | N12: =I12*L12 -> 16000 | O12: =M12-N12 -> 4484
A13: ORD-0012 | B13: 44950 | C13: =YEAR(B13) -> 2023 | D13: =CHOOSE(MONTH(B13),"01 Jan","02 Feb","03 Mar","04 Apr","05 May","06 Jun","07 Jul","08 Aug","09 Sep","10 Oct","11 Nov","12 Dec") -> 01 Jan | E13: West | F13: Furniture | G13: Standing Desk | H13: Pooja Mehta | I13: 1 | J13: 18400 | K13: 0.05 | L13: 12500 | M13: =I13*J13*(1-K13) -> 17480 | N13: =I13*L13 -> 12500 | O13: =M13-N13 -> 4980
... A901: ORD-0900 | B901: 46018 | C901: =YEAR(B901) -> 2025 | D901: =CHOOSE(MONTH(B901),"01 Jan","02 Feb","03 Mar","04 Apr","05 May","06 Jun","07 Jul","08 Aug","09 Sep","10 Oct","11 Nov","12 Dec") -> 12 Dec | E901: South | F901: Stationery | G901: Notebook Pack | H901: Karthik Iyer | I901: 16 | J901: 460 | K901: 0.1 | L901: 250 | M901: =I901*J901*(1-K901) -> 6624 | N901: =I901*L901 -> 4000 | O901: =M901-N901 -> 2624

Sheet Guide
B1: SALES DASHBOARD — PROJECT GUIDE
B2: 1. Workbook map
B3: Dashboard – KPI cards, 4 charts, Region scorecard, Top-5 products, and a panel reserved for slicers.
B4: Pivots – 4 real PivotTables sharing one cache: by Region, by Month, by Product, by Category (Revenue, Profit; Region also counts Orders).
B5: Calc – Formula layer that reads the pivots and ignores their Total rows, so charts stay correct however the pivots are filtered.
B6: Sales_Data – 900 sales rows (table tblSales). Blue font = inputs; black = formulas (Year, Month, Revenue, Cost, Profit).
B7: 2. Add slicers (about one minute)
B8: a) Go to the Pivots sheet and click inside any PivotTable.
B9: b) PivotTable Analyze ▸ Insert Slicer ▸ tick Year, Region, Category (add Sales Rep or Product if you like) ▸ OK.
B10: c) Right-click each slicer ▸ Report Connections ▸ tick ALL four PivotTables (pvRegion, pvMonth, pvProduct, pvCategory) ▸ OK.
B11: d) Cut each slicer (Ctrl+X) and paste (Ctrl+V) onto the Dashboard sheet inside the 'SLICER ZONE'. Resize to fit; Slicer ▸ Columns can make them compact.
B12: e) Click slicer buttons: every pivot filters, the Calc layer updates, and all KPIs, charts and tables on the Dashboard change instantly.
... B22: Pivot labels read 'Sum - Revenue' etc. Excel may rename these on refresh (e.g. 'Sum of Revenue'); the Calc layer reads by position, so nothing breaks.
